LICENSE.txt
MANIFEST.in
README.md
pyproject.toml
setup.cfg
setup.py
rengine/method.py
rengine/test.py
rengine.egg-info/PKG-INFO
rengine.egg-info/SOURCES.txt
rengine.egg-info/dependency_links.txt
rengine.egg-info/requires.txt
rengine.egg-info/top_level.txt