Metadata-Version: 2.1
Name: rengine
Version: 0.1.5
Summary: Most used methods for recommendation engine
Home-page: UNKNOWN
Author: Rafi Mochamad Fahreza
Author-email: prokodingproject@gmail.com
License: UNKNOWN
Keywords: algorithm,recommendation,engine
Platform: UNKNOWN
Classifier: Development Status :: 3 - Alpha
Classifier: Intended Audience :: Developers
Classifier: Topic :: Scientific/Engineering :: Artificial Intelligence 
Classifier: Programming Language :: Python :: 3
Classifier: Programming Language :: Python :: 3.6
Classifier: Programming Language :: Python :: 3.7
Classifier: Programming Language :: Python :: 3.8
Requires-Python: >=3
